lib_version_group3/__init__.py
lib_version_group3/version.py
lib_version_group3-0.1.7.dist-info/LICENSE
lib_version_group3-0.1.7.dist-info/METADATA
lib_version_group3-0.1.7.dist-info/WHEEL
lib_version_group3-0.1.7.dist-info/RECORD
