Metadata-Version: 2.1
Name: lib_version_group3
Version: 0.1.7
Summary: A Python library for managing and retrieving the software version.
License: MIT
Author: smtan
Author-email: tan.stevenmitchell@gmail.com
Requires-Python: >=3.8,<3.13
Classifier: License :: OSI Approved :: MIT License
Classifier: Programming Language :: Python :: 3
Classifier: Programming Language :: Python :: 3.8
Classifier: Programming Language :: Python :: 3.9
Classifier: Programming Language :: Python :: 3.10
Classifier: Programming Language :: Python :: 3.11
Classifier: Programming Language :: Python :: 3.12
